llm_adapters/__init__.py
llm_adapters/abstract_adapters/__init__.py
llm_adapters/abstract_adapters/adapter.py
llm_adapters/abstract_adapters/api_key_adapter_mixin.py
llm_adapters/abstract_adapters/openai_sdk_chat_adapter.py
llm_adapters/abstract_adapters/provider_adapter_mixin.py
llm_adapters/abstract_adapters/sdk_chat_adapter.py
llm_adapters/adapter_factory.py
llm_adapters/client.py
llm_adapters/client_cache.py
llm_adapters/constants.py
llm_adapters/custom_sdk_chat_provider_adapter.py
llm_adapters/general_utils.py
llm_adapters/provider_adapters/__init__.py
llm_adapters/provider_adapters/ai21_sdk_chat_provider_adapter.py
llm_adapters/provider_adapters/anthropic_sdk_chat_provider_adapter.py
llm_adapters/provider_adapters/azure_sdk_chat_provider_adapter.py
llm_adapters/provider_adapters/bigmodel_provider_adapter.py
llm_adapters/provider_adapters/cerebras_sdk_chat_provider_adapter.py
llm_adapters/provider_adapters/cohere_sdk_chat_provider_adapter.py
llm_adapters/provider_adapters/databricks_sdk_chat_provider_adapter.py
llm_adapters/provider_adapters/deepinfra_sdk_chat_provider_adapter.py
llm_adapters/provider_adapters/deepseek_sdk_chat_provider_adapter.py
llm_adapters/provider_adapters/fireworks_sdk_chat_provider_adapter.py
llm_adapters/provider_adapters/gemini_sdk_chat_provider_adapter.py
llm_adapters/provider_adapters/groq_sdk_chat_provider_adapter.py
llm_adapters/provider_adapters/lambdalabs_sdk_chat_provider_adapter.py
llm_adapters/provider_adapters/lepton_sdk_chat_provider_adapter.py
llm_adapters/provider_adapters/moescape_sdk_chat_provider_adapter.py
llm_adapters/provider_adapters/moonshot_sdk_chat_provider_adapter.py
llm_adapters/provider_adapters/octoai_sdk_chat_provider_adapter.py
llm_adapters/provider_adapters/openai_sdk_chat_provider_adapter.py
llm_adapters/provider_adapters/openrouter_sdk_chat_provider_adapter.py
llm_adapters/provider_adapters/perplexity_sdk_chat_provider_adapter.py
llm_adapters/provider_adapters/tensoropera_sdk_chat_provider_adapter.py
llm_adapters-8.14.0.dist-info/LICENSE
llm_adapters-8.14.0.dist-info/METADATA
llm_adapters-8.14.0.dist-info/WHEEL
llm_adapters-8.14.0.dist-info/RECORD
